timetools/__init__.py
timetools/pdv/__init__.py
timetools/pdv/generator/__init__.py
timetools/pdv/generator/general.py
timetools/pdv/generator/parameters.py
timetools/pdv/generator/ituTG8263/__init__.py
timetools/pdv/generator/ituTG8263/flicker.py
timetools/pdv/visualization/__init__.py
timetools/pdv/visualization/general.py
timetools/signalProcessing/__init__.py
timetools/signalProcessing/autocorrelation.py
timetools/signalProcessing/exceptions.py
timetools/signalProcessing/jobQueue.py
timetools/signalProcessing/sampling.py
timetools/signalProcessing/time.py
timetools/signalProcessing/tolerance.py
timetools/signalProcessing/chronology/__init__.py
timetools/signalProcessing/chronology/chronology.py
timetools/signalProcessing/chronology/sampling.py
timetools/synchronization/__init__.py
timetools/synchronization/clock.py
timetools/synchronization/frequency.py
timetools/synchronization/intervals.py
timetools/synchronization/time.py
timetools/synchronization/analysis/__init__.py
timetools/synchronization/analysis/fastMtie.py
timetools/synchronization/analysis/fastTdev.py
timetools/synchronization/analysis/ituTG810.py
timetools/synchronization/analysis/mtieKernels.py
timetools/synchronization/analysis/tdevKernels.py
timetools/synchronization/compliance/__init__.py
timetools/synchronization/compliance/analysis.py
timetools/synchronization/compliance/general.py
timetools/synchronization/compliance/visualization.py
timetools/synchronization/compliance/frequency/__init__.py
timetools/synchronization/compliance/frequency/masks.py
timetools/synchronization/compliance/ituTG8261/__init__.py
timetools/synchronization/compliance/ituTG8261/deploymentCase1/__init__.py
timetools/synchronization/compliance/ituTG8261/deploymentCase1/wanderBudget.py
timetools/synchronization/compliance/ituTG8261/deploymentCase2/__init__.py
timetools/synchronization/compliance/ituTG8261/deploymentCase2/wanderBudget.py
timetools-0.6.0.dist-info/DESCRIPTION.rst
timetools-0.6.0.dist-info/METADATA
timetools-0.6.0.dist-info/RECORD
timetools-0.6.0.dist-info/WHEEL
timetools-0.6.0.dist-info/metadata.json
timetools-0.6.0.dist-info/top_level.txt
