Metadata-Version: 2.0
Name: timetools
Version: 0.6.0
Summary: Python utilities relating to synchronization analysis and visualization
Home-page: https://github.com/blueskyjunkie/timetools
Author: Russell Smiley
Author-email: im.russell.smiley@gmail.com
License: GPLV3
Download-URL: https://zenodo.org/search?page=1&size=20&q=timetools
Keywords: synchronization,visualization,analysis,PDV,MTIE,TDEV
Platform: UNKNOWN
Classifier: Development Status :: 2 - Pre-Alpha
Classifier: Intended Audience :: Developers
Classifier: Topic :: System :: Hardware
Classifier: License :: OSI Approved :: GNU General Public License v3 (GPLv3)
Classifier: Programming Language :: Python :: 3
Classifier: Programming Language :: Python :: 3.3
Classifier: Programming Language :: Python :: 3.4
Requires-Dist: numpy
Requires-Dist: scipy
Requires-Dist: matplotlib
Provides-Extra: dev
Requires-Dist: zest.releaser[recommended]; extra == 'dev'
Requires-Dist: Sphinx; extra == 'dev'
Requires-Dist: setuptools; extra == 'dev'
Requires-Dist: setuptools-git; extra == 'dev'
Provides-Extra: test
Requires-Dist: nose; extra == 'test'
Requires-Dist: nose-exclude; extra == 'test'
